herakoi/__init__.py
herakoi/__main__.py
herakoi/core.py
herakoi-0.2.0.dist-info/LICENSE.md
herakoi-0.2.0.dist-info/METADATA
herakoi-0.2.0.dist-info/WHEEL
herakoi-0.2.0.dist-info/entry_points.txt
herakoi-0.2.0.dist-info/top_level.txt
herakoi-0.2.0.dist-info/RECORD
