Metadata-Version: 2.1
Name: herakoi
Version: 0.2.0
Summary: A sonification tool
Author-email: Michele Ginolfi <micheleginolfi@gmail.com>, Luca Di Mascolo <lucadimascolo@gmail.com>
License: MIT License
Project-URL: Homepage, https://github.com/lucadimascolo/herakoi
Project-URL: Bug Tracker, https://github.com/lucadimascolo/herakoi/issues
Classifier: Programming Language :: Python :: 3
Classifier: License :: OSI Approved :: MIT License
Classifier: Development Status :: 4 - Beta
Classifier: Operating System :: OS Independent
Requires-Python: >=3.7
License-File: LICENSE.md
Requires-Dist: mido (>=1.2)
Requires-Dist: python-rtmidi (==1.4.9)
Requires-Dist: opencv-python (>=4.6)
Requires-Dist: numpy (>=1.23)
Requires-Dist: pynput (>=1.7)
Requires-Dist: mediapipe ; platform_system != "Darwin" or platform_machine != "arm64"
Requires-Dist: mediapipe-silicon ; platform_system == "Darwin" and platform_machine == "arm64"
